dds.py
deepdataspace/__init__.py
deepdataspace-0.0.2.dist-info/LICENSE
deepdataspace-0.0.2.dist-info/METADATA
deepdataspace-0.0.2.dist-info/WHEEL
deepdataspace-0.0.2.dist-info/entry_points.txt
deepdataspace-0.0.2.dist-info/top_level.txt
deepdataspace-0.0.2.dist-info/RECORD
