Metadata-Version: 2.1
Name: deepdataspace
Version: 0.0.2
Summary: A tool for CV dataset labeling, visualizing and analysing
Home-page: https://idea.edu.cn/cvr.html
Author: cvr@idea
Author-email: huweiqiang@idea.edu.cn
License: UNKNOWN
Platform: UNKNOWN
Classifier: Development Status :: 4 - Beta
Classifier: Intended Audience :: Information Technology
Classifier: Intended Audience :: Science/Research
Classifier: Topic :: Scientific/Engineering :: Artificial Intelligence
Classifier: Topic :: Scientific/Engineering :: Image Processing
Classifier: Topic :: Scientific/Engineering :: Image Recognition
Classifier: Topic :: Scientific/Engineering :: Information Analysis
Classifier: Topic :: Scientific/Engineering :: Visualization
Classifier: Operating System :: MacOS :: MacOS X
Classifier: Operating System :: POSIX :: Linux
Classifier: Operating System :: Microsoft :: Windows
Classifier: Programming Language :: Python :: 3
Classifier: Programming Language :: Python :: 3.8
Classifier: Programming Language :: Python :: 3.9
Classifier: Programming Language :: Python :: 3.10
Requires-Dist: celery (==5.2.7)
Requires-Dist: click (==8.1.3)
Requires-Dist: cryptography (==39.0.1)
Requires-Dist: Django (==4.1.1)
Requires-Dist: djangorestframework (==3.14.0)
Requires-Dist: django-cors-headers (==3.13.0)
Requires-Dist: numpy (==1.21.5)
Requires-Dist: opencv-contrib-python-headless (==4.6.0.66)
Requires-Dist: opencv-python-headless (==4.6.0.66)
Requires-Dist: psutil (==5.9.2)
Requires-Dist: pydantic (==1.10.2)
Requires-Dist: pymongo (==4.2.0)
Requires-Dist: PyYAML (==6.0)
Requires-Dist: Pillow (==8.4.0)
Requires-Dist: redis (==4.3.4)
Requires-Dist: requests (==2.28.1)
Requires-Dist: scikit-learn (==1.0.2)
Requires-Dist: sentry-sdk (==1.19.1)
Requires-Dist: tqdm (==4.64.1)
Requires-Dist: whitenoise (==6.2.0)
